pythonbasic_dangitspang/__init__.py
pythonbasic_dangitspang/pythonbasic.py
pythonbasic_dangitspang-0.0.1.dist-info/LICENSE.txt
pythonbasic_dangitspang-0.0.1.dist-info/METADATA
pythonbasic_dangitspang-0.0.1.dist-info/WHEEL
pythonbasic_dangitspang-0.0.1.dist-info/top_level.txt
pythonbasic_dangitspang-0.0.1.dist-info/RECORD
