Metadata-Version: 2.1
Name: pythonbasic_dangitspang
Version: 0.0.1
Summary: A better way to write in TI-Basic
Author: Owen Gold
Project-URL: Homepage, https://github.com/DangItsPang/pythonbasic
Classifier: Programming Language :: Python :: 3
Classifier: License :: OSI Approved :: MIT License
Classifier: Operating System :: OS Independent
Requires-Python: >=3.8
License-File: LICENSE.txt
